scio_generate_cdxgen_sbom_pipeline/__init__.py
scio_generate_cdxgen_sbom_pipeline/generate_cdxgen_sbom.py
scio_generate_cdxgen_sbom_pipeline-0.0.15.dist-info/licenses/LICENSE
scio_generate_cdxgen_sbom_pipeline-0.0.15.dist-info/METADATA
scio_generate_cdxgen_sbom_pipeline-0.0.15.dist-info/WHEEL
scio_generate_cdxgen_sbom_pipeline-0.0.15.dist-info/entry_points.txt
scio_generate_cdxgen_sbom_pipeline-0.0.15.dist-info/top_level.txt
scio_generate_cdxgen_sbom_pipeline-0.0.15.dist-info/RECORD
